aliyunsdkvpcpeer/__init__.py
aliyunsdkvpcpeer/endpoint.py
aliyunsdkvpcpeer/request/__init__.py
aliyunsdkvpcpeer/request/v20220101/AcceptVpcPeerConnectionRequest.py
aliyunsdkvpcpeer/request/v20220101/CreateVpcPeerConnectionRequest.py
aliyunsdkvpcpeer/request/v20220101/DeleteVpcPeerConnectionRequest.py
aliyunsdkvpcpeer/request/v20220101/GetVpcPeerConnectionAttributeRequest.py
aliyunsdkvpcpeer/request/v20220101/ListTagResourcesRequest.py
aliyunsdkvpcpeer/request/v20220101/ListVpcPeerConnectionsRequest.py
aliyunsdkvpcpeer/request/v20220101/ModifyVpcPeerConnectionRequest.py
aliyunsdkvpcpeer/request/v20220101/MoveResourceGroupRequest.py
aliyunsdkvpcpeer/request/v20220101/RejectVpcPeerConnectionRequest.py
aliyunsdkvpcpeer/request/v20220101/TagResourcesRequest.py
aliyunsdkvpcpeer/request/v20220101/UnTagResourcesRequest.py
aliyunsdkvpcpeer/request/v20220101/__init__.py
aliyun_python_sdk_vpcpeer-1.0.3.dist-info/LICENSE
aliyun_python_sdk_vpcpeer-1.0.3.dist-info/METADATA
aliyun_python_sdk_vpcpeer-1.0.3.dist-info/WHEEL
aliyun_python_sdk_vpcpeer-1.0.3.dist-info/top_level.txt
aliyun_python_sdk_vpcpeer-1.0.3.dist-info/RECORD
